MANIFEST.in
README.md
setup.py
DataAPI/Commodity.py
DataAPI/Equity.py
DataAPI/Future.py
DataAPI/General.py
DataAPI/HedgeFund.py
DataAPI/Index.py
DataAPI/InstrumentInfo.py
DataAPI/MarketDataLoader.py
DataAPI/MasterDataLoader.py
DataAPI/MutualFund.py
DataAPI/Snapshots.py
DataAPI/SqlExpressions.py
DataAPI/Themes.py
DataAPI/Utilities.py
DataAPI/__init__.py
DataAPI/api.py
DataAPI.egg-info/PKG-INFO
DataAPI.egg-info/SOURCES.txt
DataAPI.egg-info/dependency_links.txt
DataAPI.egg-info/requires.txt
DataAPI.egg-info/top_level.txt
DataAPI/tests/__init__.py
DataAPI/tests/testCommodity.py
DataAPI/tests/testEquity.py
DataAPI/tests/testFuture.py
DataAPI/tests/testGeneral.py
DataAPI/tests/testHedgeFund.py
DataAPI/tests/testIndex.py
DataAPI/tests/testInstrumentInfo.py
DataAPI/tests/testMutualFund.py
DataAPI/tests/testSnapshots.py
DataAPI/tests/testSqlExpressions.py
DataAPI/tests/testSuite.py
DataAPI/tests/testThemes.py
doc/DataAPI.pdf
requirements/py2.txt
requirements/py3.txt