Metadata-Version: 1.0
Name: DataAPI
Version: 0.8.2
Summary: DataAPI 0.8.2
Home-page: UNKNOWN
Author: Dongxing Securities Co., Ltd.
Author-email: licheng@dxzq.net.cn
License: UNKNOWN
Platform: UNKNOWN
